castoranalytics/__init__.py
castoranalytics/app.py
castoranalytics/core/__init__.py
castoranalytics/core/api/__init__.py
castoranalytics/core/api/castorapiclient.py
castoranalytics/core/api/country.py
castoranalytics/core/api/countrycodes.py
castoranalytics/core/api/study.py
castoranalytics/core/api/studydetails.py
castoranalytics/core/api/studysite.py
castoranalytics/core/cache.py
castoranalytics/core/core.py
castoranalytics/core/db/__init__.py
castoranalytics/core/db/datamanager.py
castoranalytics/core/db/engine.py
castoranalytics/core/db/models/basemodel.py
castoranalytics/core/db/session.py
castoranalytics/core/logging.py
castoranalytics/core/singleton.py
castoranalytics/core/utils.py
castoranalytics/ui/__init__.py
castoranalytics/ui/bootstrap.py
castoranalytics/ui/components/__init__.py
castoranalytics/ui/components/backgroundimage.py
castoranalytics/ui/components/numerictablewidgetitem.py
castoranalytics/ui/constants.py
castoranalytics/ui/mainwindow.py
castoranalytics/ui/pages/__init__.py
castoranalytics/ui/pages/basepage.py
castoranalytics/ui/pages/route.py
castoranalytics/ui/pages/router.py
castoranalytics/ui/pages/settingspage.py
castoranalytics/ui/pages/studylistpage.py
castoranalytics/ui/pages/studypage.py
castoranalytics/ui/pages/studysitelistpage.py
castoranalytics/ui/resources/images/home.png
castoranalytics/ui/resources/images/icons/castoranalytics.icns
castoranalytics/ui/resources/images/icons/castoranalytics.ico
castoranalytics/ui/resources/images/icons/spinner.gif
castoranalytics/ui/resources/VERSION
castoranalytics/ui/utils.py
castoranalytics-2.0.1.dist-info/entry_points.txt
castoranalytics-2.0.1.dist-info/METADATA
castoranalytics-2.0.1.dist-info/WHEEL
castoranalytics-2.0.1.dist-info/RECORD
